[
    {
        "id": "en_GB_amnesiac",
        "name": "Amnesiac",
        "ability": "You do not know what your ability is. Each day, privately guess what it is: you learn how accurate you are.",
        "firstNightReminder": "?",
        "otherNightReminder": "?",
        "reminders": [
            "?"
        ],
        "firstNight": 40,
        "otherNight": 54,
        "team": "townsfolk",
        "edition": "experimental",
        "setup": false,
        "image": "https://raw.githubusercontent.com/taloy42/BotC-Scripts/main/Resources/Icons/amnesiac.png"
    },
    {
        "id": "en_GB_artist",
        "name": "Artist",
        "ability": "Once per game, during the day, privately ask the Storyteller any yes/no question.",
        "firstNightReminder": "",
        "otherNightReminder": "",
        "reminders": [
            "No ability"
        ],
        "firstNight": -1,
        "otherNight": -1,
        "team": "townsfolk",
        "edition": "snv",
        "setup": false,
        "image": "https://raw.githubusercontent.com/taloy42/BotC-Scripts/main/Resources/Icons/artist.png"
    },
    {
        "id": "en_GB_balloonist",
        "name": "Balloonist",
        "ability": "Each night, you learn 1 player of each character type, until there are no more types to learn. [+1 Outsider]",
        "firstNightReminder": "Show any player",
        "otherNightReminder": "Show a player with a different character type to previously",
        "reminders": [
            "Seen Townsfolk",
            "Seen Outsider",
            "Seen Minion",
            "Seen Demon",
            "Seen Traveller"
        ],
        "firstNight": 55,
        "otherNight": 69,
        "team": "townsfolk",
        "edition": "experimental",
        "setup": true,
        "image": "https://raw.githubusercontent.com/taloy42/BotC-Scripts/main/Resources/Icons/balloonist.png"
    },
    {
        "id": "en_GB_baron",
        "name": "Baron",
        "ability": "There are extra Outsiders in play. [+2 Outsiders]",
        "firstNightReminder": "",
        "otherNightReminder": "",
        "reminders": [],
        "firstNight": -1,
        "otherNight": -1,
        "team": "minion",
        "edition": "tb",
        "setup": true,
        "image": "https://raw.githubusercontent.com/taloy42/BotC-Scripts/main/Resources/Icons/baron.png"
    },
    {
        "id": "en_GB_cannibal",
        "name": "Cannibal",
        "ability": "You have the ability of the recently killed executee. If they are evil, you are poisoned until a good player dies by execution.",
        "firstNightReminder": "",
        "otherNightReminder": "",
        "reminders": [
            "Poisoned",
            "Died today"
        ],
        "firstNight": -1,
        "otherNight": -1,
        "team": "townsfolk",
        "edition": "experimental",
        "setup": false,
        "image": "https://raw.githubusercontent.com/taloy42/BotC-Scripts/main/Resources/Icons/cannibal.png"
    },
    {
        "id": "en_GB_drunk",
        "name": "Drunk",
        "ability": "You do not know you are the Drunk. You think you are a Townsfolk character, but you are not.",
        "firstNightReminder": "",
        "otherNightReminder": "",
        "reminders": [
            "Drunk"
        ],
        "firstNight": -1,
        "otherNight": -1,
        "team": "outsider",
        "edition": "tb",
        "setup": true,
        "image": "https://raw.githubusercontent.com/taloy42/BotC-Scripts/main/Resources/Icons/drunk.png"
    },
    {
        "id": "en_GB_empath",
        "name": "Empath",
        "ability": "Each night, you learn how many of your 2 alive neighbours are evil.",
        "firstNightReminder": "Give a finger signal.",
        "otherNightReminder": "Give a finger signal.",
        "reminders": [],
        "firstNight": 45,
        "otherNight": 60,
        "team": "townsfolk",
        "edition": "tb",
        "setup": false,
        "image": "https://raw.githubusercontent.com/taloy42/BotC-Scripts/main/Resources/Icons/empath.png"
    },
    {
        "id": "en_GB_fisherman",
        "name": "Fisherman",
        "ability": "Once per game, during the day, visit the Storyteller for some advice to help you win.",
        "firstNightReminder": "",
        "otherNightReminder": "",
        "reminders": [
            "No ability"
        ],
        "firstNight": -1,
        "otherNight": -1,
        "team": "townsfolk",
        "edition": "experimental",
        "setup": false,
        "image": "https://raw.githubusercontent.com/taloy42/BotC-Scripts/main/Resources/Icons/fisherman.png"
    },
    {
        "id": "en_GB_general",
        "name": "General",
        "ability": "Each night, you learn which alignment the Storyteller believes is winning: good, evil, or neither.",
        "firstNightReminder": "Give a thumb signal.",
        "otherNightReminder": "Give a thumb signal.",
        "reminders": [],
        "firstNight": 61,
        "otherNight": 77,
        "team": "townsfolk",
        "edition": "experimental",
        "setup": false,
        "image": "https://raw.githubusercontent.com/taloy42/BotC-Scripts/main/Resources/Icons/general.png"
    },
    {
        "id": "en_GB_goblin",
        "name": "Goblin",
        "ability": "If you publicly claim to be the Goblin when nominated & are executed that day, your team wins.",
        "firstNightReminder": "",
        "otherNightReminder": "",
        "reminders": [
            "Claimed"
        ],
        "firstNight": -1,
        "otherNight": -1,
        "team": "minion",
        "edition": "experimental",
        "setup": false,
        "image": "https://raw.githubusercontent.com/taloy42/BotC-Scripts/main/Resources/Icons/goblin.png"
    },
    {
        "id": "en_GB_leviathan",
        "name": "Leviathan",
        "ability": "If more than 1 good player is executed, you win. All players know you are in play. After day 5, evil wins.",
        "firstNightReminder": "Declare that \"The Leviathan is in play.\" Mark the Leviathan with the DAY 1 reminder.",
        "otherNightReminder": "Optionally, declare that \"The Leviathan is in play.\" Replace the reminder token.",
        "reminders": [
            "Day 1",
            "Day 2",
            "Day 3",
            "Day 4",
            "Day 5",
            "Good player executed"
        ],
        "firstNight": 65,
        "otherNight": 81,
        "team": "demon",
        "edition": "experimental",
        "setup": false,
        "image": "https://raw.githubusercontent.com/taloy42/BotC-Scripts/main/Resources/Icons/leviathan.png"
    },
    {
        "id": "en_GB_lunatic",
        "name": "Lunatic",
        "ability": "You think you are a Demon, but you are not. The Demon knows who you are & who you choose at night.",
        "firstNightReminder": "If there are 7 or more players, wake the Lunatic: Show the THESE ARE YOUR MINIONS token. Point to any players. Show the THESE CHARACTERS ARE NOT IN PLAY token. Show 3 good character tokens. Put the Lunatic to sleep. Wake the Demon. Show the YOU ARE info token and the Demon token. Show the THIS PLAYER IS info token and the Lunatic token, then point to the Lunatic.",
        "otherNightReminder": "Do whatever needs to be done to simulate the Demon acting. Put the Lunatic to sleep. Wake the Demon. Show the Lunatic token & point to them, then their target(s).",
        "reminders": [
            "Attack 1",
            "Attack 2",
            "Attack 3"
        ],
        "firstNight": 15,
        "otherNight": 27,
        "team": "outsider",
        "edition": "bmr",
        "setup": false,
        "image": "https://raw.githubusercontent.com/taloy42/BotC-Scripts/main/Resources/Icons/lunatic.png"
    },
    {
        "id": "en_GB_mutant",
        "name": "Mutant",
        "ability": "If you are “mad” about being an Outsider, you might be executed.",
        "firstNightReminder": "",
        "otherNightReminder": "",
        "reminders": [],
        "firstNight": -1,
        "otherNight": -1,
        "team": "outsider",
        "edition": "snv",
        "setup": false,
        "image": "https://raw.githubusercontent.com/taloy42/BotC-Scripts/main/Resources/Icons/mutant.png"
    },
    {
        "id": "en_GB_philosopher",
        "name": "Philosopher",
        "ability": "Once per game, at night, choose a good character: gain that ability. If this character is in play, they are drunk.",
        "firstNightReminder": "The Philosopher might choose a character. If necessary, swap their character token.",
        "otherNightReminder": "The Philosopher might choose a character. If necessary, swap their character token.",
        "reminders": [
            "Drunk",
            "Is the Philosopher"
        ],
        "firstNight": 9,
        "otherNight": 8,
        "team": "townsfolk",
        "edition": "snv",
        "setup": false,
        "image": "https://raw.githubusercontent.com/taloy42/BotC-Scripts/main/Resources/Icons/philosopher.png"
    },
    {
        "id": "en_GB_saint",
        "name": "Saint",
        "ability": "If you die by execution, your team loses.",
        "firstNightReminder": "",
        "otherNightReminder": "",
        "reminders": [],
        "firstNight": -1,
        "otherNight": -1,
        "team": "outsider",
        "edition": "tb",
        "setup": false,
        "image": "https://raw.githubusercontent.com/taloy42/BotC-Scripts/main/Resources/Icons/saint.png"
    },
    {
        "id": "en_GB_savant",
        "name": "Savant",
        "ability": "Each day, you may visit the Storyteller to learn 2 things in private: 1 is true & 1 is false.",
        "firstNightReminder": "",
        "otherNightReminder": "",
        "reminders": [],
        "firstNight": -1,
        "otherNight": -1,
        "team": "townsfolk",
        "edition": "snv",
        "setup": false,
        "image": "https://raw.githubusercontent.com/taloy42/BotC-Scripts/main/Resources/Icons/savant.png"
    },
    {
        "id": "en_GB_scarletwoman",
        "name": "Scarlet Woman",
        "ability": "If there are 5 or more players alive & the Demon dies, you become the Demon. (Travellers don’t count)",
        "firstNightReminder": "",
        "otherNightReminder": "If the Scarlet Woman became the Imp today, show them the YOU ARE token, then the Imp token.",
        "reminders": [
            "Demon"
        ],
        "firstNight": -1,
        "otherNight": 26,
        "team": "minion",
        "edition": "tb",
        "setup": false,
        "image": "https://raw.githubusercontent.com/taloy42/BotC-Scripts/main/Resources/Icons/scarletwoman.png"
    },
    {
        "id": "en_GB_seamstress",
        "name": "Seamstress",
        "ability": "Once per game, at night, choose 2 players (not yourself): you learn if they are the same alignment.",
        "firstNightReminder": "The Seamstress might choose 2 players. Nod or shake your head.",
        "otherNightReminder": "The Seamstress might choose 2 players. Nod or shake your head.",
        "reminders": [
            "No ability"
        ],
        "firstNight": 51,
        "otherNight": 67,
        "team": "townsfolk",
        "edition": "snv",
        "setup": false,
        "image": "https://raw.githubusercontent.com/taloy42/BotC-Scripts/main/Resources/Icons/seamstress.png"
    },
    {
        "id": "en_GB_slayer",
        "name": "Slayer",
        "ability": "Once per game, during the day, publicly choose a player: if they are the Demon, they die.",
        "firstNightReminder": "",
        "otherNightReminder": "",
        "reminders": [
            "No ability"
        ],
        "firstNight": -1,
        "otherNight": -1,
        "team": "townsfolk",
        "edition": "tb",
        "setup": false,
        "image": "https://raw.githubusercontent.com/taloy42/BotC-Scripts/main/Resources/Icons/slayer.png"
    },
    {
        "id": "en_GB_snakecharmer",
        "name": "Snake Charmer",
        "ability": "Each night, choose an alive player: a chosen Demon swaps characters & alignments with you & is then poisoned.",
        "firstNightReminder": "The Snake Charmer chooses a player. If they chose the Demon: Show the YOU ARE & Demon tokens. Give a thumbs down. Swap the Snake Charmer & Demon tokens. Put the old Snake Charmer to sleep. Wake the old Demon. Show the YOU ARE and Snake Charmer tokens & give a thumbs up.",
        "otherNightReminder": "The Snake Charmer chooses a player. If they chose the Demon: Show the YOU ARE & Demon tokens. Give a thumbs down. Swap the Snake Charmer & Demon tokens. Put the old Snake Charmer to sleep. Wake the old Demon. Show the YOU ARE and Snake Charmer tokens & give a thumbs up.",
        "reminders": [
            "Poisoned"
        ],
        "firstNight": 27,
        "otherNight": 17,
        "team": "townsfolk",
        "edition": "snv",
        "setup": false,
        "image": "https://raw.githubusercontent.com/taloy42/BotC-Scripts/main/Resources/Icons/snakecharmer.png"
    },
    {
        "id": "en_GB_undertaker",
        "name": "Undertaker",
        "ability": "Each night*, you learn which character died by execution today.",
        "firstNightReminder": "",
        "otherNightReminder": "If a player was executed today, show their character token.",
        "reminders": [
            "Executed"
        ],
        "firstNight": -1,
        "otherNight": 62,
        "team": "townsfolk",
        "edition": "tb",
        "setup": false,
        "image": "https://raw.githubusercontent.com/taloy42/BotC-Scripts/main/Resources/Icons/undertaker.png"
    },
    {
        "id": "en_GB_widow",
        "name": "Widow",
        "ability": "On your 1st night, look at the Grimoire and choose a player: they are poisoned. 1 good player knows a Widow is in play.",
        "firstNightReminder": "Show the Grimoire for as long as the Widow needs. The Widow chooses a player.",
        "otherNightReminder": "",
        "reminders": [
            "Poisoned",
            "Knows"
        ],
        "firstNight": 25,
        "otherNight": -1,
        "team": "minion",
        "edition": "experimental",
        "setup": false,
        "image": "https://raw.githubusercontent.com/taloy42/BotC-Scripts/main/Resources/Icons/widow.png"
    }
]