[
    {
        "id": "en_GB_beggar",
        "name": "Beggar",
        "ability": "You must use a vote token to vote. Dead players may choose to give you theirs. If so, you learn their alignment. You are sober & healthy.",
        "firstNightReminder": "",
        "otherNightReminder": "",
        "reminders": [],
        "firstNight": -1,
        "otherNight": -1,
        "team": "traveller",
        "edition": "experimental",
        "setup": false,
        "image": "https://raw.githubusercontent.com/taloy42/BotC-Scripts/main/Resources/Icons/beggar.png"
    },
    {
        "id": "en_GB_bureaucrat",
        "name": "Bureaucrat",
        "ability": "Each night, choose a player (not yourself): their vote counts as 3 votes tomorrow.",
        "firstNightReminder": "The Bureaucrat chooses a player.",
        "otherNightReminder": "The Bureaucrat chooses a player.",
        "reminders": [
            "3 votes"
        ],
        "firstNight": 7,
        "otherNight": 5,
        "team": "traveller",
        "edition": "experimental",
        "setup": false,
        "image": "https://raw.githubusercontent.com/taloy42/BotC-Scripts/main/Resources/Icons/bureaucrat.png"
    },
    {
        "id": "en_GB_butler",
        "name": "Butler",
        "ability": "Each night, choose a player (not yourself): tomorrow, you may only vote if they are voting too.",
        "firstNightReminder": "The Butler chooses a player.",
        "otherNightReminder": "The Butler chooses a player.",
        "reminders": [
            "Master"
        ],
        "firstNight": 47,
        "otherNight": 74,
        "team": "outsider",
        "edition": "tb",
        "setup": false,
        "image": "https://raw.githubusercontent.com/taloy42/BotC-Scripts/main/Resources/Icons/butler.png"
    },
    {
        "id": "en_GB_cerenovus",
        "name": "Cerenovus",
        "ability": "Each night, choose a player & a good character: they are “mad” they are this character tomorrow, or might be executed.",
        "firstNightReminder": "The Cerenovus chooses a player & a character. Put the Cerenovus to sleep. Wake the target. Show the THIS CHARACTER SELECTED YOU token, the Cerenovus token, then the madness-character token.",
        "otherNightReminder": "The Cerenovus chooses a player & a character. Put the Cerenovus to sleep. Wake the target. Show the THIS CHARACTER SELECTED YOU token, the Cerenovus token, then the madness-character token.",
        "reminders": [
            "Mad"
        ],
        "firstNight": 32,
        "otherNight": 21,
        "team": "minion",
        "edition": "snv",
        "setup": false,
        "image": "https://raw.githubusercontent.com/taloy42/BotC-Scripts/main/Resources/Icons/cerenovus.png"
    },
    {
        "id": "en_GB_chef",
        "name": "Chef",
        "ability": "You start knowing how many pairs of evil players there are.",
        "firstNightReminder": "Give a finger signal.",
        "otherNightReminder": "",
        "reminders": [],
        "firstNight": 44,
        "otherNight": -1,
        "team": "townsfolk",
        "edition": "tb",
        "setup": false,
        "image": "https://raw.githubusercontent.com/taloy42/BotC-Scripts/main/Resources/Icons/chef.png"
    },
    {
        "id": "en_GB_drunk",
        "name": "Drunk",
        "ability": "You do not know you are the Drunk. You think you are a Townsfolk character, but you are not.",
        "firstNightReminder": "",
        "otherNightReminder": "",
        "reminders": [
            "Drunk"
        ],
        "firstNight": -1,
        "otherNight": -1,
        "team": "outsider",
        "edition": "tb",
        "setup": true,
        "image": "https://raw.githubusercontent.com/taloy42/BotC-Scripts/main/Resources/Icons/drunk.png"
    },
    {
        "id": "en_GB_empath",
        "name": "Empath",
        "ability": "Each night, you learn how many of your 2 alive neighbours are evil.",
        "firstNightReminder": "Give a finger signal.",
        "otherNightReminder": "Give a finger signal.",
        "reminders": [],
        "firstNight": 45,
        "otherNight": 60,
        "team": "townsfolk",
        "edition": "tb",
        "setup": false,
        "image": "https://raw.githubusercontent.com/taloy42/BotC-Scripts/main/Resources/Icons/empath.png"
    },
    {
        "id": "en_GB_eviltwin",
        "name": "Evil Twin",
        "ability": "You & an opposing player know each other. If the good player is executed, evil wins. Good can't win if you both live.",
        "firstNightReminder": "Wake both twins. Allow eye contact. Show the good twin's character token to the Evil Twin & vice versa.",
        "otherNightReminder": "",
        "reminders": [
            "Twin"
        ],
        "firstNight": 30,
        "otherNight": -1,
        "team": "minion",
        "edition": "snv",
        "setup": false,
        "image": "https://raw.githubusercontent.com/taloy42/BotC-Scripts/main/Resources/Icons/eviltwin.png"
    },
    {
        "id": "en_GB_fanggu",
        "name": "Fang Gu",
        "ability": "Each night*, choose a player: they die. The 1st Outsider this kills becomes an evil Fang Gu & you die instead. [+1 Outsider]",
        "firstNightReminder": "",
        "otherNightReminder": "The Fang Gu chooses a player. If they chose an Outsider (once only): Replace the Outsider token with the spare Fang Gu token. Put the Fang Gu to sleep. Wake the target. Show the YOU ARE and Fang Gu tokens & give a thumbs-down.",
        "reminders": [
            "Dead",
            "Once"
        ],
        "firstNight": -1,
        "otherNight": 36,
        "team": "demon",
        "edition": "snv",
        "setup": true,
        "image": "https://raw.githubusercontent.com/taloy42/BotC-Scripts/main/Resources/Icons/fanggu.png"
    },
    {
        "id": "en_GB_fortuneteller",
        "name": "Fortune Teller",
        "ability": "Each night, choose 2 players: you learn if either is a Demon. There is a good player that registers as a Demon to you.",
        "firstNightReminder": "The Fortune Teller chooses 2 players. Nod if either is the Demon (or the RED HERRING).",
        "otherNightReminder": "The Fortune Teller chooses 2 players. Nod if either is the Demon (or the RED HERRING).",
        "reminders": [
            "Red herring"
        ],
        "firstNight": 46,
        "otherNight": 61,
        "team": "townsfolk",
        "edition": "tb",
        "setup": false,
        "image": "https://raw.githubusercontent.com/taloy42/BotC-Scripts/main/Resources/Icons/fortuneteller.png"
    },
    {
        "id": "en_GB_gunslinger",
        "name": "Gunslinger",
        "ability": "Each day, after the 1st vote has been tallied, you may choose a player that voted: they die.",
        "firstNightReminder": "",
        "otherNightReminder": "",
        "reminders": [],
        "firstNight": -1,
        "otherNight": -1,
        "team": "traveller",
        "edition": "experimental",
        "setup": false,
        "image": "https://raw.githubusercontent.com/taloy42/BotC-Scripts/main/Resources/Icons/gunslinger.png"
    },
    {
        "id": "en_GB_investigator",
        "name": "Investigator",
        "ability": "You start knowing that 1 of 2 players is a particular Minion.",
        "firstNightReminder": "Show the Minion character token. Point to both the MINION and WRONG players.",
        "otherNightReminder": "",
        "reminders": [
            "Minion",
            "Wrong"
        ],
        "firstNight": 43,
        "otherNight": -1,
        "team": "townsfolk",
        "edition": "tb",
        "setup": false,
        "image": "https://raw.githubusercontent.com/taloy42/BotC-Scripts/main/Resources/Icons/investigator.png"
    },
    {
        "id": "en_GB_librarian",
        "name": "Librarian",
        "ability": "You start knowing that 1 of 2 players is a particular Outsider. (Or that zero are in play.)",
        "firstNightReminder": "Show the Outsider character token. Point to both the OUTSIDER and WRONG players.",
        "otherNightReminder": "",
        "reminders": [
            "Outsider",
            "Wrong"
        ],
        "firstNight": 42,
        "otherNight": -1,
        "team": "townsfolk",
        "edition": "tb",
        "setup": false,
        "image": "https://raw.githubusercontent.com/taloy42/BotC-Scripts/main/Resources/Icons/librarian.png"
    },
    {
        "id": "en_GB_mayor",
        "name": "Mayor",
        "ability": "If only 3 players live & no execution occurs, your team wins. If you die at night, another player might die instead.",
        "firstNightReminder": "",
        "otherNightReminder": "",
        "reminders": [],
        "firstNight": -1,
        "otherNight": -1,
        "team": "townsfolk",
        "edition": "tb",
        "setup": false,
        "image": "https://raw.githubusercontent.com/taloy42/BotC-Scripts/main/Resources/Icons/mayor.png"
    },
    {
        "id": "en_GB_monk",
        "name": "Monk",
        "ability": "Each night*, choose a player (not yourself): they are safe from the Demon tonight.",
        "firstNightReminder": "",
        "otherNightReminder": "The Monk chooses a player.",
        "reminders": [
            "Protected"
        ],
        "firstNight": -1,
        "otherNight": 18,
        "team": "townsfolk",
        "edition": "tb",
        "setup": false,
        "image": "https://raw.githubusercontent.com/taloy42/BotC-Scripts/main/Resources/Icons/monk.png"
    },
    {
        "id": "en_GB_nodashii",
        "name": "No Dashii",
        "ability": "Each night*, choose a player: they die. Your 2 Townsfolk neighbours are poisoned.",
        "firstNightReminder": "",
        "otherNightReminder": "The No Dashii chooses a player.",
        "reminders": [
            "Dead",
            "Poisoned"
        ],
        "firstNight": -1,
        "otherNight": 37,
        "team": "demon",
        "edition": "snv",
        "setup": false,
        "image": "https://raw.githubusercontent.com/taloy42/BotC-Scripts/main/Resources/Icons/nodashii.png"
    },
    {
        "id": "en_GB_pithag",
        "name": "Pit-Hag",
        "ability": "Each night*, choose a player & a character they become (if not-in-play). If a Demon is made, deaths tonight are arbitrary.",
        "firstNightReminder": "",
        "otherNightReminder": "The Pit-Hag chooses a player & a character. If they chose a character that is not in play: Put the Pit-Hag to sleep. Wake the target. Show the YOU ARE token & their new character token.",
        "reminders": [],
        "firstNight": -1,
        "otherNight": 22,
        "team": "minion",
        "edition": "snv",
        "setup": false,
        "image": "https://raw.githubusercontent.com/taloy42/BotC-Scripts/main/Resources/Icons/pithag.png"
    },
    {
        "id": "en_GB_ravenkeeper",
        "name": "Ravenkeeper",
        "ability": "If you die at night, you are woken to choose a player: you learn their character.",
        "firstNightReminder": "",
        "otherNightReminder": "If the Ravenkeeper died tonight, the Ravenkeeper chooses a player. Show that player's character token.",
        "reminders": [],
        "firstNight": -1,
        "otherNight": 59,
        "team": "townsfolk",
        "edition": "tb",
        "setup": false,
        "image": "https://raw.githubusercontent.com/taloy42/BotC-Scripts/main/Resources/Icons/ravenkeeper.png"
    },
    {
        "id": "en_GB_recluse",
        "name": "Recluse",
        "ability": "You might register as evil & as a Minion or Demon, even if dead.",
        "firstNightReminder": "",
        "otherNightReminder": "",
        "reminders": [],
        "firstNight": -1,
        "otherNight": -1,
        "team": "outsider",
        "edition": "tb",
        "setup": false,
        "image": "https://raw.githubusercontent.com/taloy42/BotC-Scripts/main/Resources/Icons/recluse.png"
    },
    {
        "id": "en_GB_saint",
        "name": "Saint",
        "ability": "If you die by execution, your team loses.",
        "firstNightReminder": "",
        "otherNightReminder": "",
        "reminders": [],
        "firstNight": -1,
        "otherNight": -1,
        "team": "outsider",
        "edition": "tb",
        "setup": false,
        "image": "https://raw.githubusercontent.com/taloy42/BotC-Scripts/main/Resources/Icons/saint.png"
    },
    {
        "id": "en_GB_scapegoat",
        "name": "Scapegoat",
        "ability": "If a player of your alignment is executed, you might be executed instead.",
        "firstNightReminder": "",
        "otherNightReminder": "",
        "reminders": [],
        "firstNight": -1,
        "otherNight": -1,
        "team": "traveller",
        "edition": "experimental",
        "setup": false,
        "image": "https://raw.githubusercontent.com/taloy42/BotC-Scripts/main/Resources/Icons/scapegoat.png"
    },
    {
        "id": "en_GB_slayer",
        "name": "Slayer",
        "ability": "Once per game, during the day, publicly choose a player: if they are the Demon, they die.",
        "firstNightReminder": "",
        "otherNightReminder": "",
        "reminders": [
            "No ability"
        ],
        "firstNight": -1,
        "otherNight": -1,
        "team": "townsfolk",
        "edition": "tb",
        "setup": false,
        "image": "https://raw.githubusercontent.com/taloy42/BotC-Scripts/main/Resources/Icons/slayer.png"
    },
    {
        "id": "en_GB_soldier",
        "name": "Soldier",
        "ability": "You are safe from the Demon.",
        "firstNightReminder": "",
        "otherNightReminder": "",
        "reminders": [],
        "firstNight": -1,
        "otherNight": -1,
        "team": "townsfolk",
        "edition": "tb",
        "setup": false,
        "image": "https://raw.githubusercontent.com/taloy42/BotC-Scripts/main/Resources/Icons/soldier.png"
    },
    {
        "id": "en_GB_thief",
        "name": "Thief",
        "ability": "Each night, choose a player (not yourself): their vote counts negatively tomorrow.",
        "firstNightReminder": "The Thief chooses a player.",
        "otherNightReminder": "The Thief chooses a player.",
        "reminders": [
            "Negative vote"
        ],
        "firstNight": 8,
        "otherNight": 7,
        "team": "traveller",
        "edition": "experimental",
        "setup": false,
        "image": "https://raw.githubusercontent.com/taloy42/BotC-Scripts/main/Resources/Icons/thief.png"
    },
    {
        "id": "en_GB_undertaker",
        "name": "Undertaker",
        "ability": "Each night*, you learn which character died by execution today.",
        "firstNightReminder": "",
        "otherNightReminder": "If a player was executed today, show their character token.",
        "reminders": [
            "Executed"
        ],
        "firstNight": -1,
        "otherNight": 62,
        "team": "townsfolk",
        "edition": "tb",
        "setup": false,
        "image": "https://raw.githubusercontent.com/taloy42/BotC-Scripts/main/Resources/Icons/undertaker.png"
    },
    {
        "id": "en_GB_vigormortis",
        "name": "Vigormortis",
        "ability": "Each night*, choose a player: they die. Minions you kill keep their ability & poison 1 Townsfolk neighbour. [−1 Outsider]",
        "firstNightReminder": "",
        "otherNightReminder": "The Vigormortis chooses a player. If that player is a Minion, poison a neighboring Townsfolk.",
        "reminders": [
            "Dead",
            "Has ability",
            "Poisoned"
        ],
        "firstNight": -1,
        "otherNight": 39,
        "team": "demon",
        "edition": "snv",
        "setup": true,
        "image": "https://raw.githubusercontent.com/taloy42/BotC-Scripts/main/Resources/Icons/vigormortis.png"
    },
    {
        "id": "en_GB_virgin",
        "name": "Virgin",
        "ability": "The 1st time you are nominated, if the nominator is a Townsfolk, they are executed immediately.",
        "firstNightReminder": "",
        "otherNightReminder": "",
        "reminders": [
            "No ability"
        ],
        "firstNight": -1,
        "otherNight": -1,
        "team": "townsfolk",
        "edition": "tb",
        "setup": false,
        "image": "https://raw.githubusercontent.com/taloy42/BotC-Scripts/main/Resources/Icons/virgin.png"
    },
    {
        "id": "en_GB_vortox",
        "name": "Vortox",
        "ability": "Each night*, choose a player: they die. Townsfolk abilities yield false info. Each day, if no-one is executed, evil wins.",
        "firstNightReminder": "",
        "otherNightReminder": "The Vortox chooses a player.",
        "reminders": [
            "Dead"
        ],
        "firstNight": -1,
        "otherNight": 38,
        "team": "demon",
        "edition": "snv",
        "setup": false,
        "image": "https://raw.githubusercontent.com/taloy42/BotC-Scripts/main/Resources/Icons/vortox.png"
    },
    {
        "id": "en_GB_washerwoman",
        "name": "Washerwoman",
        "ability": "You start knowing that 1 of 2 players is a particular Townsfolk.",
        "firstNightReminder": "Show the Townsfolk character token. Point to both the TOWNSFOLK and WRONG players.",
        "otherNightReminder": "",
        "reminders": [
            "Townsfolk",
            "Wrong"
        ],
        "firstNight": 41,
        "otherNight": -1,
        "team": "townsfolk",
        "edition": "tb",
        "setup": false,
        "image": "https://raw.githubusercontent.com/taloy42/BotC-Scripts/main/Resources/Icons/washerwoman.png"
    },
    {
        "id": "en_GB_witch",
        "name": "Witch",
        "ability": "Each night, choose a player: if they nominate tomorrow, they die. If just 3 players live, you lose this ability.",
        "firstNightReminder": "The Witch chooses a player.",
        "otherNightReminder": "The Witch chooses a player.",
        "reminders": [
            "Cursed"
        ],
        "firstNight": 31,
        "otherNight": 20,
        "team": "minion",
        "edition": "snv",
        "setup": false,
        "image": "https://raw.githubusercontent.com/taloy42/BotC-Scripts/main/Resources/Icons/witch.png"
    }
]